sabyenc.so
sabyenc-3.3.6.dist-info/WHEEL
sabyenc-3.3.6.dist-info/top_level.txt
sabyenc-3.3.6.dist-info/METADATA
sabyenc-3.3.6.dist-info/RECORD
