Metadata-Version: 1.1
Name: sabyenc
Version: 3.3.6
Summary: yEnc Module for Python modified for SABnzbd
Home-page: https://github.com/sabnzbd/sabnzbd-yenc
Author: Safihre
Author-email: safihre@sabnzbd.org
License: LGPLv3
Platform: UNKNOWN
Classifier: Programming Language :: Python
Classifier: Programming Language :: Python :: 2.7
Classifier: Programming Language :: C
Classifier: License :: OSI Approved :: GNU Lesser General Public License v3 (LGPLv3)
Classifier: Operating System :: Unix
Classifier: Development Status :: 5 - Production/Stable
Classifier: Environment :: Plugins
Classifier: Topic :: Software Development :: Libraries :: Python Modules
Classifier: Topic :: Communications :: Usenet News
